admin_image_preview/__init__.py
admin_image_preview/apps.py
admin_image_preview/models.py
admin_image_preview/readme.md
admin_image_preview/migrations/__init__.py
admin_image_preview/static/admin_image_preview/image_preview.js
admin_image_preview/templates/admin/change_form.html
admin_image_preview/templates/admin/original_change_form.html
admin_form_image_preivew-1.5.dist-info/LICENSE.txt
admin_form_image_preivew-1.5.dist-info/METADATA
admin_form_image_preivew-1.5.dist-info/WHEEL
admin_form_image_preivew-1.5.dist-info/top_level.txt
admin_form_image_preivew-1.5.dist-info/RECORD
