Metadata-Version: 2.1
Name: admin-form-image-preivew
Version: 1.5
Summary: Sami Test Pip
Home-page: https://github.com/humblesami/admin_form_image_preivew.git
Author: Sami Akram
Author-email: Sami Akram <samiakram@live.com>
Maintainer-email: Sami Akram <samiakram@live.com>
Project-URL: Changelog, https://github.com/humblesami/admin_form_image_preivew/CHANGES.rst
Project-URL: Code, https://github.com/humblesami/admin_form_image_preivew
Project-URL: Issue tracker, https://github.com/humblesami/admin_form_image_preivew/issues
Keywords: urllib,httplib,http
Classifier: Operating System :: OS Independent
Classifier: Programming Language :: Python :: 3.5
Requires-Python: >=3.6
License-File: LICENSE.txt
Requires-Dist: Django (>=3)
Requires-Dist: Pillow (>=8)
Provides-Extra: deploy
Requires-Dist: bump2version ; extra == 'deploy'
Requires-Dist: readme-renderer[md] ; extra == 'deploy'
Requires-Dist: git-changelog ; extra == 'deploy'
Provides-Extra: development
Requires-Dist: Django (>=3) ; extra == 'development'
Requires-Dist: Pillow (>=8) ; extra == 'development'
Requires-Dist: bump2version ; extra == 'development'
Requires-Dist: readme-renderer[md] ; extra == 'development'
Requires-Dist: git-changelog ; extra == 'development'
